Metadata-Version: 1.0
Name: learn-probability-distribution
Version: 0.1
Summary: Gaussian and Binomial distributions
Home-page: UNKNOWN
Author: Ankit Hans
Author-email: ankithans1947@gmail.com
License: UNKNOWN
Platform: UNKNOWN
